README.txt
setup.py
scripts/tls.py
scripts/tlsdb.py
tlslite/BaseDB.py
tlslite/Checker.py
tlslite/FileObject.py
tlslite/HandshakeSettings.py
tlslite/Session.py
tlslite/SessionCache.py
tlslite/SharedKeyDB.py
tlslite/TLSConnection.py
tlslite/TLSRecordLayer.py
tlslite/VerifierDB.py
tlslite/X509.py
tlslite/X509CertChain.py
tlslite/__init__.py
tlslite/api.py
tlslite/constants.py
tlslite/errors.py
tlslite/mathtls.py
tlslite/messages.py
tlslite.egg-info/PKG-INFO
tlslite.egg-info/SOURCES.txt
tlslite.egg-info/dependency_links.txt
tlslite.egg-info/native_libs.txt
tlslite.egg-info/top_level.txt
tlslite/utils/win32prng.c
tlslite/integration/AsyncStateMachine.py
tlslite/integration/ClientHelper.py
tlslite/integration/HTTPTLSConnection.py
tlslite/integration/IMAP4_TLS.py
tlslite/integration/IntegrationHelper.py
tlslite/integration/POP3_TLS.py
tlslite/integration/SMTP_TLS.py
tlslite/integration/TLSAsyncDispatcherMixIn.py
tlslite/integration/TLSSocketServerMixIn.py
tlslite/integration/TLSTwistedProtocolWrapper.py
tlslite/integration/XMLRPCTransport.py
tlslite/integration/__init__.py
tlslite/utils/AES.py
tlslite/utils/ASN1Parser.py
tlslite/utils/Cryptlib_AES.py
tlslite/utils/Cryptlib_RC4.py
tlslite/utils/Cryptlib_TripleDES.py
tlslite/utils/OpenSSL_AES.py
tlslite/utils/OpenSSL_RC4.py
tlslite/utils/OpenSSL_RSAKey.py
tlslite/utils/OpenSSL_TripleDES.py
tlslite/utils/PyCrypto_AES.py
tlslite/utils/PyCrypto_RC4.py
tlslite/utils/PyCrypto_RSAKey.py
tlslite/utils/PyCrypto_TripleDES.py
tlslite/utils/Python_AES.py
tlslite/utils/Python_RC4.py
tlslite/utils/Python_RSAKey.py
tlslite/utils/RC4.py
tlslite/utils/RSAKey.py
tlslite/utils/TripleDES.py
tlslite/utils/__init__.py
tlslite/utils/cipherfactory.py
tlslite/utils/codec.py
tlslite/utils/compat.py
tlslite/utils/cryptomath.py
tlslite/utils/dateFuncs.py
tlslite/utils/hmac.py
tlslite/utils/jython_compat.py
tlslite/utils/keyfactory.py
tlslite/utils/rijndael.py
tlslite/utils/win32prng.c
tlslite/utils/xmltools.py