Metadata-Version: 1.0
Name: tlslite
Version: 0.3.8
Summary: tlslite implements SSL and TLS with SRP, shared-keys, cryptoID, or X.509 authentication.
Home-page: http://trevp.net/tlslite/
Author: Trevor Perrin
Author-email: trevp@trevp.net
License: public domain
Platform: UNKNOWN
